build/lib/ttclient/__init__.py
build/lib/ttclient/abc.py
build/lib/ttclient/base.py
build/lib/ttclient/client.py
build/lib/ttclient/exceptions.py
ttclient/__init__.py
ttclient/abc.py
ttclient/base.py
ttclient/client.py
ttclient/exceptions.py
ttclient-0.4.dist-info/licenses/LICENSE.md
ttclient-0.4.dist-info/METADATA
ttclient-0.4.dist-info/WHEEL
ttclient-0.4.dist-info/entry_points.txt
ttclient-0.4.dist-info/top_level.txt
ttclient-0.4.dist-info/RECORD
