Metadata-Version: 2.4
Name: ttclient
Version: 0.4
Summary: Chat client
Author-email: Tamtam team <support@tamtamteam.com>
License: MIT License
Keywords: async,bot
Classifier: Development Status :: 4 - Beta
Classifier: Environment :: Plugins
Classifier: Intended Audience :: Developers
Classifier: License :: OSI Approved :: MIT License
Classifier: Programming Language :: Python
Classifier: Programming Language :: Python :: 3
Classifier: Programming Language :: Python :: 3.12
Classifier: Programming Language :: Python :: 3.13
Classifier: Topic :: Software Development :: Libraries :: Python Modules
Classifier: Framework :: AsyncIO
Requires-Python: >=3.12
License-File: LICENSE.md
Requires-Dist: httpx
Requires-Dist: ttutils
Provides-Extra: dev
Requires-Dist: pytest-runner; extra == "dev"
Requires-Dist: pytest; extra == "dev"
Requires-Dist: pytest-asyncio; extra == "dev"
Requires-Dist: pytest-cov; extra == "dev"
Requires-Dist: ruff; extra == "dev"
Requires-Dist: mypy; extra == "dev"
Dynamic: license-file
